Workbook

Sheet Cover
B1: CLOUDPULSE SaaS ANALYTICS
B2: CLOUDPULSE SaaS ANALYTICS
B4: SaaS Revenue & KPI Financial Model | ARR, Cohort & Unit Economics Analysis
B5: B2B SaaS | SMB & Mid-Market Segments | Subscription Revenue Focus
B8: KEY SaaS METRICS SNAPSHOT
B9: KPI | C9: FY2024A | D9: FY2025E | E9: FY2026E
B10: ARR ($mm) | C10: ='ARR & MRR'!E11 -> 68.6 | D10: ='ARR & MRR'!F11 -> 97.5 | E10: ='ARR & MRR'!G11 -> 136.1
B11: ARR Growth YoY | C11: ='ARR & MRR'!E12 -> 0.42323651 | D11: ='ARR & MRR'!F12 -> 0.4212828 | E11: ='ARR & MRR'!G12 -> 0.28361499
B12: Monthly Recurring Revenue ($mm) | C12: ='ARR & MRR'!E11/12 -> 5.7166667 | D12: ='ARR & MRR'!F11/12 -> 8.125 | E12: ='ARR & MRR'!G11/12 -> 11.341667
B13: Net Revenue Retention | C13: ='ARR & MRR'!E33 -> 1.18 | D13: ='ARR & MRR'!F33 -> 1.21 | E13: ='ARR & MRR'!G33 -> 1.24
B14: Gross Revenue Retention | C14: ='ARR & MRR'!E34 -> 0.88 | D14: ='ARR & MRR'!F34 -> 0.89 | E14: ='ARR & MRR'!G34 -> 0.9
B15: Logo Churn Rate | C15: 0.12 | D15: 0.11 | E15: 0.1
B16: CAC Payback Period (months) | C16: 18 | D16: 16 | E16: 14
B17: LTV / CAC Ratio | C17: 4.2 | D17: 5.1 | E17: 6.2
B18: Rule of 40 Score | C18: 58 | D18: 67 | E18: 75

Sheet ARR & MRR
B1: CLOUDPULSE: ARR WATERFALL AND SUBSCRIPTION METRICS
B2: All figures in USD millions unless noted | Annual Recurring Revenue Bridge
B4: ARR WATERFALL ($mm)
B5: Metric | C5: FY2022A | D5: FY2023A | E5: FY2024A | F5: FY2025E | G5: FY2026E | H5: FY2027E
B6: Beginning ARR | C6: 23.8 | D6: 33.9 | E6: 48.2 | F6: 68.6 | G6: 97.5 | H6: 136.1
B7: New ARR (New Logos) | C7: 8.2 | D7: 10.4 | E7: 13.8 | F7: 18.2 | G7: 23.8 | H7: 30.4
B8: Expansion ARR (Upsell) | C8: 4.8 | D8: 6.2 | E8: 8.6 | F8: 11.4 | G8: 15.2 | H8: 20.1
B9: Contraction ARR | C9: -1.2 | D9: -1.4 | E9: -1.8 | F9: -2.2 | G9: -2.8 | H9: -3.4
B10: Churned ARR | C10: -2.8 | D10: -3.4 | E10: -4.2 | F10: -5.2 | G10: -6.4 | H10: -7.8
B11: Ending ARR | C11: 33.9 | D11: 48.2 | E11: 68.6 | F11: 97.5 | G11: 136.1 | H11: 188.2
B12: ARR Growth YoY | C12: N/A | D12: =(D11-C11)/C11 -> 0.42182891 | E12: =(E11-D11)/D11 -> 0.42323651 | F12: =(F11-E11)/E11 -> 0.4212828 | G12: =(G11-F11)/G11 -> 0.28361499 | H12: =(H11-G11)/H11 -> 0.27683316
B14: MONTHLY RECURRING REVENUE & BOOKINGS
B15: Metric | C15: FY2022A | D15: FY2023A | E15: FY2024A | F15: FY2025E | G15: FY2026E | H15: FY2027E
B16: Monthly Recurring Revenue (MRR) | C16: 2.8 | D16: 4 | E16: 5.7 | F16: 8.1 | G16: 11.3 | H16: 15.7
B17: MRR Growth YoY | D17: =(D16-C16)/C16 -> 0.42857143 | E17: =(E16-D16)/D16 -> 0.425 | F17: =(F16-E16)/F16 -> 0.2962963 | G17: =(G16-F16)/G16 -> 0.28318584 | H17: =(H16-G16)/H16 -> 0.28025478
B18: Annual Contract Value (ACV, $mm) | C18: 2.4 | D18: 3.2 | E18: 4.1 | F18: 5.6 | G18: 7.4 | H18: 9.8
B19: Total Bookings ($mm) | C19: 11.2 | D19: 15.8 | E19: 21.8 | F19: 30.2 | G19: 41.4 | H19: 55.6
B20: Book-to-Bill Ratio | C20: =C19/C16/12 -> 0.33333333 | D20: =D19/D16/12 -> 0.32916667 | E20: =E19/E16/12 -> 0.31871345 | F20: =F19/F16/12 -> 0.31069959 | G20: =G19/G16/12 -> 0.30530973 | H20: =H19/H16/12 -> 0.29511677
B22: CUSTOMER / LOGO METRICS
B23: Metric | C23: FY2022A | D23: FY2023A | E23: FY2024A | F23: FY2025E | G23: FY2026E | H23: FY2027E
B24: Beginning Logos | C24: 142 | D24: 198 | E24: 268 | F24: 356 | G24: 468 | H24: 608
B25: New Logos Added | C25: 68 | D25: 84 | E25: 108 | F25: 136 | G25: 168 | H25: 208
B26: Churned Logos | C26: 12 | D26: 14 | E26: 20 | F26: 24 | G26: 28 | H26: 34
B27: Ending Logos (Customers) | C27: 198 | D27: 268 | E27: 356 | F27: 468 | G27: 608 | H27: 782
B28: Logo Churn Rate | C28: =C26/C24 -> 0.084507042 | D28: =D26/D24 -> 0.070707071 | E28: =E26/E24 -> 0.074626866 | F28: =F26/F24 -> 0.06741573 | G28: =G26/G24 -> 0.05982906 | H28: =H26/H24 -> 0.055921053
B29: Average ARR per Customer ($K) | C29: =C11/C27*1000 -> 171.21212 | D29: =D11/D27*1000 -> 179.85075 | E29: =E11/E27*1000 -> 192.69663 | F29: =F11/F27*1000 -> 208.33333 | G29: =G11/G27*1000 -> 223.84868 | H29: =H11/H27*1000 -> 240.66496
B31: RETENTION & COHORT METRICS
B32: Metric | C32: FY2022A | D32: FY2023A | E32: FY2024A | F32: FY2025E | G32: FY2026E | H32: FY2027E
B33: Net Revenue Retention (NRR) | C33: 1.12 | D33: 1.14 | E33: 1.18 | F33: 1.21 | G33: 1.24 | H33: 1.27
B34: Gross Revenue Retention (GRR) | C34: 0.85 | D34: 0.86 | E34: 0.88 | F34: 0.89 | G34: 0.9 | H34: 0.91
B35: Net Dollar Expansion Rate | C35: =C33-C34 -> 0.27 | D35: =D33-D34 -> 0.28 | E35: =E33-E34 -> 0.3 | F35: =F33-F34 -> 0.32 | G35: =G33-G34 -> 0.34 | H35: =H33-H34 -> 0.36
B36: Quick Ratio (New+Exp / Churn+Contr) | C36: =(C7+C8)/(ABS(C9)+ABS(C10)) -> 3.25 | D36: =(D7+D8)/(ABS(D9)+ABS(D10)) -> 3.4583333 | E36: =(E7+E8)/(ABS(E9)+ABS(E10)) -> 3.7333333 | F36: =(F7+F8)/(ABS(F9)+ABS(F10)) -> 4 | G36: =(G7+G8)/(ABS(G9)+ABS(G10)) -> 4.2391304 | H36: =(H7+H8)/(ABS(H9)+ABS(H10)) -> 4.5089286

Sheet Unit Economics
B1: CLOUDPULSE: UNIT ECONOMICS AND LTV/CAC ANALYSIS
B3: CUSTOMER ACQUISITION COSTS (CAC)
B4: Metric | C4: FY2022A | D4: FY2023A | E4: FY2024A | F4: FY2025E | G4: FY2026E | H4: FY2027E
B5: S&M Spend ($mm) | C5: 8.2 | D5: 10.8 | E5: 14.2 | F5: 18.4 | G5: 23.6 | H5: 30.1
B6: New Customers Acquired | C6: 68 | D6: 84 | E6: 108 | F6: 136 | G6: 168 | H6: 208
B7: Blended CAC ($K) | C7: =C5*1000/C6 -> 120.58824 | D7: =D5*1000/D6 -> 128.57143 | E7: =E5*1000/E6 -> 131.48148 | F7: =F5*1000/F6 -> 135.29412 | G7: =G5*1000/G6 -> 140.47619 | H7: =H5*1000/H6 -> 144.71154
B8: Avg. New ARR per Customer ($K) | C8: 28.4 | D8: 31.2 | E8: 36.8 | F8: 41.4 | G8: 46.2 | H8: 52.8
B9: Payback Period (months) | C9: =C7/(C8/12) -> 50.952775 | D9: =D7/(D8/12) -> 49.450549 | E9: =E7/(E8/12) -> 42.874396 | F9: =F7/(F8/12) -> 39.215686 | G9: =G7/(G8/12) -> 36.487322 | H9: =H7/(H8/12) -> 32.888986
B11: CUSTOMER LIFETIME VALUE (LTV)
B12: Metric | C12: FY2022A | D12: FY2023A | E12: FY2024A | F12: FY2025E | G12: FY2026E | H12: FY2027E
B13: Gross Margin % | C13: 0.68 | D13: 0.7 | E13: 0.724 | F13: 0.741 | G13: 0.758 | H13: 0.772
B14: Avg. Contract Life (years) | C14: 4.2 | D14: 4.6 | E14: 5.1 | F14: 5.8 | G14: 6.4 | H14: 7.1
B15: Annual Gross Profit / Customer ($K) | C15: =C8*C13 -> 19.312 | D15: =D8*D13 -> 21.84 | E15: =E8*E13 -> 26.6432 | F15: =F8*F13 -> 30.6774 | G15: =G8*G13 -> 35.0196 | H15: =H8*H13 -> 40.7616
B16: LTV ($K) | C16: =C15*C14 -> 81.1104 | D16: =D15*D14 -> 100.464 | E16: =E15*E14 -> 135.88032 | F16: =F15*F14 -> 177.92892 | G16: =G15*G14 -> 224.12544 | H16: =H15*H14 -> 289.40736
B17: LTV / CAC Ratio | C17: =C16/C7 -> 0.67262283 | D17: =D16/D7 -> 0.78138667 | E17: =E16/E7 -> 1.033456 | F17: =F16/F7 -> 1.3151268 | G17: =G16/G7 -> 1.5954692 | H17: =H16/H7 -> 1.9998914
B19: SEGMENT ANALYSIS: SMB vs. MID-MARKET
B20: SMB Segment (Less than $10K ACV) | F20: Mid-Market ($10K to $100K ACV)
C21: FY2024A | D21: FY2025E | E21: FY2026E | F21: FY2024A | G21: FY2025E | H21: FY2026E
B22: % of Logos | C22: 0.72 | D22: 0.71 | E22: 0.7 | F22: 0.28 | G22: 0.29 | H22: 0.3
B23: % of ARR | C23: 0.34 | D23: 0.33 | E23: 0.31 | F23: 0.66 | G23: 0.67 | H23: 0.69
B24: Avg. ACV ($K) | C24: 4.2 | D24: 4.8 | E24: 5.2 | F24: 42 | G24: 48 | H24: 55
B25: Logo Churn | C25: 0.18 | D25: 0.17 | E25: 0.16 | F25: 0.07 | G25: 0.06 | H25: 0.05
B26: NRR | C26: 1.08 | D26: 1.09 | E26: 1.11 | F26: 1.28 | G26: 1.31 | H26: 1.35
B27: CAC Payback (mo) | C27: 12 | D27: 11 | E27: 10 | F27: 22 | G27: 20 | H27: 18
B28: LTV/CAC | C28: 3.1 | D28: 3.4 | E28: 3.8 | F28: 5.8 | G28: 6.4 | H28: 7.2
B31: RULE OF 40 AND EFFICIENCY METRICS
B32: Metric | C32: FY2022A | D32: FY2023A | E32: FY2024A | F32: FY2025E | G32: FY2026E | H32: FY2027E
B33: Revenue Growth % | C33: N/A | D33: 42.8 | E33: 44.2 | F33: 42.4 | G33: 39.4 | H33: 38.1
B34: FCF Margin % | C34: -18.2 | D34: -12.4 | E34: -6.2 | F34: 1.8 | G34: 8.4 | H34: 14.2
B35: Rule of 40 Score | C35: N/A | D35: =D33+D34 -> 30.4 | E35: =E33+E34 -> 38 | F35: =F33+F34 -> 44.2 | G35: =G33+G34 -> 47.8 | H35: =H33+H34 -> 52.3
B36: Magic Number (Efficiency Score) | C36: 0.42 | D36: 0.58 | E36: 0.74 | F36: 0.88 | G36: 1.02 | H36: 1.18
B37: Burn Multiple | C37: 3.8 | D37: 2.6 | E37: 1.4 | F37: 0.8 | G37: 0.4 | H37: 0.2

Sheet Cohort Analysis
B1: CLOUDPULSE: REVENUE COHORT RETENTION ANALYSIS
B2: Revenue retention by acquisition cohort year. Values represent percentage of initial ARR retained in subsequent years.
B4: Cohort Year | C4: Yr 0 (Acq) | D4: Yr 1 | E4: Yr 2 | F4: Yr 3 | G4: Yr 4 | H4: Yr 5 | I4: Yr 6 | J4: Yr 7
B6: 2018 | C6: 1 | D6: 1.12 | E6: 1.22 | F6: 1.3 | G6: 1.36 | H6: 1.41 | I6: 1.44 | J6: 1.46
B7: 2019 | C7: 1 | D7: 1.1 | E7: 1.21 | F7: 1.29 | G7: 1.35 | H7: 1.4 | I7: 1.44
B8: 2020 | C8: 1 | D8: 1.08 | E8: 1.18 | F8: 1.27 | G8: 1.34 | H8: 1.39
B9: 2021 | C9: 1 | D9: 1.12 | E9: 1.24 | F9: 1.33 | G9: 1.39
B10: 2022 | C10: 1 | D10: 1.14 | E10: 1.27 | F10: 1.36
B11: 2023 | C11: 1 | D11: 1.16 | E11: 1.3
B12: 2024 | C12: 1 | D12: 1.18
B13: 2025E | C13: 1
B15: Average | C15: 1 | D15: 1.14 | E15: 1.24 | F15: 1.31 | G15: 1.36 | H15: 1.4 | I15: 1.44 | J15: 1.46
B17: Retention Legend: | C17: ≥140% | D17: 130-139% | E17: 120-129% | F17: 110-119% | G17: 100-109% | H17: <100% | I17: Future
B19: Initial Cohort ARR ($mm)
B20: Cohort Year | C20: 2018 | D20: 2019 | E20: 2020 | F20: 2021 | G20: 2022 | H20: 2023 | I20: 2024 | J20: 2025E
B21: Initial ARR ($mm) | C21: 2.8 | D21: 4.2 | E21: 6.1 | F21: 8.4 | G21: 11.2 | H21: 15.8 | I21: 22.4 | J21: 31.2
